audio_diffusion_pytorch_fork/__init__.py
audio_diffusion_pytorch_fork/diffusion.py
audio_diffusion_pytorch_fork/model.py
audio_diffusion_pytorch_fork/modules.py
audio_diffusion_pytorch_fork/utils.py
audio_diffusion_pytorch_fork-0.0.105.dist-info/LICENSE
audio_diffusion_pytorch_fork-0.0.105.dist-info/METADATA
audio_diffusion_pytorch_fork-0.0.105.dist-info/WHEEL
audio_diffusion_pytorch_fork-0.0.105.dist-info/top_level.txt
audio_diffusion_pytorch_fork-0.0.105.dist-info/RECORD
