Metadata-Version: 2.1
Name: audio-diffusion-pytorch-fork
Version: 0.0.105
Summary: A fork of Flavio Schneider's Audio Diffusion - PyTorch
Home-page: https://github.com/harmonai-org/audio-diffusion-pytorch-fork
Author: Harmonai
License: MIT
Keywords: artificial intelligence,deep learning,audio generation
Classifier: Development Status :: 4 - Beta
Classifier: Intended Audience :: Developers
Classifier: Topic :: Scientific/Engineering :: Artificial Intelligence
Classifier: License :: OSI Approved :: MIT License
Classifier: Programming Language :: Python :: 3.6
License-File: LICENSE
Requires-Dist: tqdm
Requires-Dist: torch >=1.6
Requires-Dist: data-science-types >=0.2
Requires-Dist: einops >=0.4
Requires-Dist: einops-exts >=0.0.3
Requires-Dist: audio-encoders-pytorch
Requires-Dist: descript-audio-codec
